README.md
mdx_figcaption_ng.py
setup.py
mdx_figcaption_ng.egg-info/PKG-INFO
mdx_figcaption_ng.egg-info/SOURCES.txt
mdx_figcaption_ng.egg-info/dependency_links.txt
mdx_figcaption_ng.egg-info/requires.txt
mdx_figcaption_ng.egg-info/top_level.txt