Metadata-Version: 1.1
Name: mdx-figcaption-ng
Version: 0.1
Summary: Extension for Python-Markdown to parse images with captions inside a figure element.
Home-page: https://github.com/Presslabs/markdown-figures
Author: anteprandium, Presslabs
Author-email: ping@presslab.com
License: UNKNOWN
Platform: UNKNOWN
Classifier: Development Status :: 4 - Beta
Classifier: Operating System :: OS Independent
Classifier: License :: OSI Approved :: GNU General Public License v2 (GPLv2)
Classifier: Intended Audience :: Developers
Classifier: Environment :: Web Environment
Classifier: Programming Language :: Python
Classifier: Topic :: Text Processing :: Filters
Classifier: Topic :: Text Processing :: Markup :: HTML
